danlp/__init__.py
danlp/about.py
danlp/download.py
danlp/utils.py
danlp/datasets/__init__.py
danlp/datasets/dacoref.py
danlp/datasets/daned.py
danlp/datasets/dannet.py
danlp/datasets/dawikined.py
danlp/datasets/ddt.py
danlp/datasets/dkhate.py
danlp/datasets/sentiment.py
danlp/datasets/unimorph.py
danlp/datasets/wiki_ann.py
danlp/datasets/word_sim.py
danlp/models/__init__.py
danlp/models/bert_models.py
danlp/models/electra_models.py
danlp/models/embeddings.py
danlp/models/flair_models.py
danlp/models/spacy_models.py
danlp/models/xlmr_models.py
danlp/models/allennlp_models/__init__.py
danlp/models/allennlp_models/version.py
danlp/models/allennlp_models/common/__init__.py
danlp/models/allennlp_models/common/ontonotes_coref.py
danlp/models/allennlp_models/coref/__init__.py
danlp/models/allennlp_models/coref/util.py
danlp/models/allennlp_models/coref/dataset_readers/__init__.py
danlp/models/allennlp_models/coref/dataset_readers/conll.py
danlp/models/allennlp_models/coref/metrics/__init__.py
danlp/models/allennlp_models/coref/metrics/conll_coref_scores.py
danlp/models/allennlp_models/coref/metrics/mention_recall.py
danlp/models/allennlp_models/coref/models/__init__.py
danlp/models/allennlp_models/coref/models/coref.py
danlp/models/allennlp_models/coref/predictors/__init__.py
danlp/models/allennlp_models/coref/predictors/coref.py
tests/__init__.py
tests/test_bert_models.py
tests/test_datasets.py
tests/test_download.py
tests/test_electra_models.py
tests/test_embeddings.py
tests/test_flair_models.py
tests/test_spacy_models.py
tests/test_xlmr_models.py
danlp-0.1.2.dist-info/LICENSE
danlp-0.1.2.dist-info/METADATA
danlp-0.1.2.dist-info/WHEEL
danlp-0.1.2.dist-info/top_level.txt
danlp-0.1.2.dist-info/RECORD
