Metadata-Version: 2.1
Name: danlp
Version: 0.1.2
Summary: DaNLP: NLP in Danish
Home-page: https://github.com/alexandrainst/danlp/
Author: Alexandra Institute
Author-email: dansknlp@alexandra.dk
License: BSD 3-Clause License
Platform: UNKNOWN
Classifier: License :: OSI Approved :: BSD License
Classifier: Programming Language :: Python :: 3 :: Only
Classifier: Programming Language :: Python :: 3.6
Classifier: Programming Language :: Python :: 3.7
Classifier: Programming Language :: Python :: 3.8
Classifier: Topic :: Scientific/Engineering :: Artificial Intelligence
Classifier: Topic :: Scientific/Engineering
Requires-Dist: conllu
Requires-Dist: pandas
Requires-Dist: pyconll
Requires-Dist: tqdm
Requires-Dist: tweepy
Requires-Dist: progressbar
Provides-Extra: all
Requires-Dist: transformers (<=4.3.3) ; extra == 'all'
Requires-Dist: gensim (<=3.8.3) ; extra == 'all'
Requires-Dist: torch (<=1.7.1) ; extra == 'all'
Requires-Dist: flair (<=0.9) ; extra == 'all'
Requires-Dist: spacy (<=2.2.3) ; extra == 'all'
Requires-Dist: allennlp (<=2.5.0) ; extra == 'all'
